{
  "chapitre": "Chapitre V.\tLa prière du voyage (çalât as-safar)",
  "contenu": [
    {
      "type": "texte",
      "contenu": "BIBLIOGRAPHIE"
    },
    {
      "type": "texte",
      "contenu": "Le Noble Coran :"
    },
    {
      "type": "texte",
      "contenu": "Al Muwata de l’Imam Malick"
    },
    {
      "type": "texte",
      "contenu": "Recueil de hadith sahih : Bukhari"
    },
    {
      "type": "texte",
      "contenu": "La Risala : Abû Muh’ammad’ Abdallâh"
    },
    {
      "type": "texte",
      "contenu": "Al-akhdari fi al-îbadat : Mukhtaçar Sidi Abderrahman"
    },
    {
      "type": "texte",
      "contenu": "CENTRE DE RECHERCHES DAARA-TAQWAA"
    },
    {
      "type": "texte",
      "contenu": "E-mail : intercogef@gmail.com"
    },
    {
      "type": "texte",
      "contenu": "Telephone : +221 76 680 00 81"
    },
    {
      "type": "texte",
      "contenu": "Enregistré au BSDA sous le N°2567 200 302"
    },
    {
      "type": "texte",
      "contenu": "Du 20 Mars 2002 (loi du 04/12/73)"
    }
  ]
}